topsis_vivek/__init__.py
topsis_vivek/topsis.py
Topsis_Vivek_102203778-0.1.0.dist-info/METADATA
Topsis_Vivek_102203778-0.1.0.dist-info/WHEEL
Topsis_Vivek_102203778-0.1.0.dist-info/entry_points.txt
Topsis_Vivek_102203778-0.1.0.dist-info/top_level.txt
Topsis_Vivek_102203778-0.1.0.dist-info/RECORD
