Metadata-Version: 2.1
Name: Topsis-Vivek-102203778
Version: 0.1.0
Summary: A Python package to perform TOPSIS analysis
Home-page: https://github.com/your-github-username/Topsis-Vivek-102203778
Author: Vivek Arora
Author-email: varora2004@gmail.com
Classifier: Programming Language :: Python :: 3
Classifier: License :: OSI Approved :: MIT License
Classifier: Operating System :: OS Independent
Requires-Python: >=3.6
Requires-Dist: numpy
Requires-Dist: pandas
